add_bom/__init__.py
add_bom/__main__.py
add_bom/cli.py
add_bom-1.0.0.dist-info/LICENSE
add_bom-1.0.0.dist-info/METADATA
add_bom-1.0.0.dist-info/WHEEL
add_bom-1.0.0.dist-info/entry_points.txt
add_bom-1.0.0.dist-info/RECORD
