Metadata-Version: 2.3
Name: add-bom
Version: 1.0.0
Summary: A simple utility to add a BOM to a file to ensure it opens as UTF-8 in Excel on a Mac
License: MIT
Author: Kaj Siebert
Author-email: kaj@k-si.com
Requires-Python: >=3.10
Classifier: License :: OSI Approved :: MIT License
Classifier: Programming Language :: Python :: 3
Classifier: Programming Language :: Python :: 3.10
Classifier: Programming Language :: Python :: 3.11
Classifier: Programming Language :: Python :: 3.12
Classifier: Programming Language :: Python :: 3.13
Requires-Dist: charset-normalizer (>=3.4.2,<4.0.0)
Requires-Dist: click (>=8.2.0,<9.0.0)
